desReg/__init__.py
desReg/dataset/Student_Marks.csv
desReg/dataset/__init__.py
desReg/dataset/load_datasets.py
desReg/des/DESRegression.py
desReg/des/__init__.py
desReg/utils/__init__.py
desReg/utils/measures.py
DESReg-0.1.1.dist-info/License.rst
DESReg-0.1.1.dist-info/METADATA
DESReg-0.1.1.dist-info/WHEEL
DESReg-0.1.1.dist-info/top_level.txt
DESReg-0.1.1.dist-info/RECORD
